README.md
setup.py
fw_core/__init__.py
fw_core/__main__.py
fw_core.egg-info/PKG-INFO
fw_core.egg-info/SOURCES.txt
fw_core.egg-info/dependency_links.txt
fw_core.egg-info/entry_points.txt
fw_core.egg-info/requires.txt
fw_core.egg-info/top_level.txt
fw_core/common/__init__.py
fw_core/common/business_validations.py
fw_core/common/exception_handler.py
fw_core/helpers/__init__.py
fw_core/helpers/database.py
fw_core/helpers/date_helpers.py
fw_core/helpers/object_helpers.py
fw_core/helpers/request_helpers.py